blade/__init__.py
blade/core.py
blade/main.py
blade_encrypt-1.0.0.dist-info/METADATA
blade_encrypt-1.0.0.dist-info/WHEEL
blade_encrypt-1.0.0.dist-info/entry_points.txt
blade_encrypt-1.0.0.dist-info/top_level.txt
blade_encrypt-1.0.0.dist-info/RECORD
