Metadata-Version: 2.1
Name: blade-encrypt
Version: 1.0.0
Summary: BLADE Encryption and Compression Tool
Author: DARKTRON
Classifier: Programming Language :: Python :: 3
Classifier: License :: OSI Approved :: MIT License
Classifier: Operating System :: OS Independent
Requires-Python: >=3.6
Requires-Dist: cryptography
Requires-Dist: fade
Requires-Dist: colorama
